README.md
setup.py
bpndtrustar/__init__.py
bpndtrustar/bpndtrustar.py
bpndtrustar.egg-info/PKG-INFO
bpndtrustar.egg-info/SOURCES.txt
bpndtrustar.egg-info/dependency_links.txt
bpndtrustar.egg-info/entry_points.txt
bpndtrustar.egg-info/not-zip-safe
bpndtrustar.egg-info/requires.txt
bpndtrustar.egg-info/top_level.txt